smartrec_client/__init__.py
smartrec_client/triton_client.py
epoch8_smartrec_client-0.1.0.dev1.dist-info/METADATA
epoch8_smartrec_client-0.1.0.dev1.dist-info/WHEEL
epoch8_smartrec_client-0.1.0.dev1.dist-info/RECORD
